jderobot_kurt-2.0.7.data/scripts/kurtc.py
jderobot_kurt-2.0.7.data/scripts/kurtgui.py
jderobot_kurt-2.0.7.dist-info/METADATA
jderobot_kurt-2.0.7.dist-info/RECORD
jderobot_kurt-2.0.7.dist-info/WHEEL
jderobot_kurt-2.0.7.dist-info/top_level.txt
kurt/__init__.py
kurt/plugin.py
kurt/text.py
kurt/scratch14/__init__.py
kurt/scratch14/blocks.py
kurt/scratch14/blockspecs_src.py
kurt/scratch14/fixed_objects.py
kurt/scratch14/heights.py
kurt/scratch14/inline_objects.py
kurt/scratch14/objtable.py
kurt/scratch14/user_objects.py
kurt/scratch20/__init__.py
kurt/scratch20/blocks.py
kurt/scratch20/commands_src.py
kurt/scratch20/commands_src_bk.py
kurt/scratch20/commands_src_extras.py
